setup.py
emcli/__init__.py
emcli/emcli.py
emcli/logger.py
emcli/storage.py
lblemcli.egg-info/PKG-INFO
lblemcli.egg-info/SOURCES.txt
lblemcli.egg-info/dependency_links.txt
lblemcli.egg-info/entry_points.txt
lblemcli.egg-info/requires.txt
lblemcli.egg-info/top_level.txt