Metadata-Version: 1.0
Name: lblemcli
Version: 0.1
Summary: A email client in terminal
Home-page: https://github.com
Author: libinglin
Author-email: libinglin@126.com
License: UNKNOWN
Platform: UNKNOWN
